affiliation_builder/__init__.py
affiliation_builder/core.py
affiliation_builder-0.2.0.dist-info/METADATA
affiliation_builder-0.2.0.dist-info/WHEEL
affiliation_builder-0.2.0.dist-info/licenses/LICENSE
affiliation_builder-0.2.0.dist-info/RECORD
