Metadata-Version: 2.4
Name: affiliation-builder
Version: 0.2.0
Summary: Build bipartite networks from JSON affiliation data
Project-URL: Homepage, https://github.com/timofruehwirth/affiliation-builder
Project-URL: Repository, https://github.com/timofruehwirth/affiliation-builder
Project-URL: Issues, https://github.com/timofruehwirth/affiliation-builder/issues
Project-URL: Documentation, https://github.com/timofruehwirth/affiliation-builder#readme
Author-email: Timo Frühwirth <timo.fruehwirth@oeaw.ac.at>
License-Expression: MIT
License-File: LICENSE
Keywords: affiliation,affiliation-network,bipartite-network,digital-humanities,json,network,network-analysis,networkx
Classifier: Development Status :: 3 - Alpha
Classifier: Intended Audience :: Science/Research
Classifier: License :: OSI Approved :: MIT License
Classifier: Operating System :: OS Independent
Classifier: Programming Language :: Python :: 3
Classifier: Programming Language :: Python :: 3.9
Classifier: Programming Language :: Python :: 3.10
Classifier: Programming Language :: Python :: 3.11
Classifier: Programming Language :: Python :: 3.12
Classifier: Topic :: Scientific/Engineering :: Information Analysis
Classifier: Topic :: Software Development :: Libraries :: Python Modules
Requires-Python: >=3.9
Requires-Dist: networkx>=3.0
Requires-Dist: requests>=2.31.0
